{
  "id": "set_cooling_operation_mode",
  "title": {
    "en": "Set cooling mode",
    "de": "Kühlbetrieb-Betriebsart setzen",
    "nl": "Koelingsmodus instellen",
    "fr": "Définir le mode refroidissement"
  },
  "args": [
    {
      "type": "device",
      "name": "device",
      "filter": "driver_id=luxtronik-heatpump"
    },
    {
      "name": "mode",
      "type": "dropdown",
      "title": {
        "en": "Mode",
        "de": "Betriebsart",
        "nl": "Modus",
        "fr": "Mode"
      },
      "values": [
        {
          "id": "0",
          "label": {
            "en": "Off",
            "de": "Aus",
            "nl": "Uit",
            "fr": "Arrêt"
          }
        },
        {
          "id": "1",
          "label": {
            "en": "Automatic",
            "de": "Automatik",
            "nl": "Automatisch",
            "fr": "Automatique"
          }
        }
      ]
    }
  ],
  "titleFormatted": {
    "en": "Set cooling mode to [[mode]]",
    "de": "Kühlbetrieb-Betriebsart auf [[mode]] setzen",
    "nl": "Koelingsmodus instellen op [[mode]]",
    "fr": "Définir le mode refroidissement sur [[mode]]"
  }
}
